causalis/__init__.py
causalis/data/__init__.py
causalis/data/causaldata.py
causalis/data/generators.py
causalis/eda/__init__.py
causalis/eda/eda.py
causalis/eda/rct_design/__init__.py
causalis/eda/rct_design/mde.py
causalis/eda/rct_design/traffic_splitter.py
causalis/inference/__init__.py
causalis/inference/ate/__init__.py
causalis/inference/ate/dml_ate.py
causalis/inference/ate/dml_ate_source.py
causalis/inference/atte/__init__.py
causalis/inference/atte/bootstrap_diff_means.py
causalis/inference/atte/conversion_z_test.py
causalis/inference/atte/dml_atte.py
causalis/inference/atte/dml_atte_source.py
causalis/inference/atte/ttest.py
causalis/inference/cate/__init__.py
causalis/inference/cate/cate_esimand.py
causalis/inference/estimators/__init__.py
causalis/inference/estimators/irm.py
causalis/inference/gate/__init__.py
causalis/inference/gate/gate_esimand.py
causalis/refutation/__init__.py
causalis/refutation/overlap/__init__.py
causalis/refutation/overlap/overlap_validation.py
causalis/refutation/score/__init__.py
causalis/refutation/score/score_validation.py
causalis/refutation/sutva/__init__.py
causalis/refutation/sutva/sutva_validation.py
causalis/refutation/unconfoundedness/__init__.py
causalis/refutation/unconfoundedness/sensitivity.py
causalis/refutation/unconfoundedness/uncofoundedness_validation.py
causalis-0.1.1.dist-info/licenses/LICENSE
causalis-0.1.1.dist-info/METADATA
causalis-0.1.1.dist-info/WHEEL
causalis-0.1.1.dist-info/top_level.txt
causalis-0.1.1.dist-info/RECORD
